[
    {
        "image":"1.png",
        "name":"Zeineb",
        "breed":"Persian",
        "animal": "Cat",
        "gender":"Female",
        "age": "5",
        "animalId": "A123455",
        "shelterId":"S123456",
        "indoor":true,
        "outdoor":false,
        "description":"Here is a description of zeineb the cat",
        "activelevel":3,
        "attentionSeeking": true,
        "neutered":false,
        "vaccinations":true,
        "abandonIssue":true
    },
    {
        "image":"1.png",
        "name":"Lily",
        "breed":"Persian",
        "animal": "Cat",
        "gender":"Female",
        "age": "5",
        "animalId": "A123455",
        "shelterId":"S123456",
        "indoor":true,
        "outdoor":false,
        "description":"Here is a description of zeineb the cat",
        "activelevel":3,
        "attentionSeeking": true,
        "neutered":false,
        "vaccinations":true,
        "abandonIssue":true
    },
    {
        "image":"1.png",
        "name":"Rosie",
        "breed":"Persian",
        "animal": "Cat",
        "gender":"Female",
        "age": "5",
        "animalId": "A123455",
        "shelterId":"S123456",
        "indoor":true,
        "outdoor":false,
        "description":"Here is a description of zeineb the cat",
        "activelevel":3,
        "attentionSeeking": true,
        "neutered":false,
        "vaccinations":true,
        "abandonIssue":true
    },
    {
        "image":"1.png",
        "name":"Michelle",
        "breed":"Persian",
        "animal": "Cat",
        "gender":"Female",
        "age": "5",
        "animalId": "A123455",
        "shelterId":"S123456",
        "indoor":true,
        "outdoor":false,
        "description":"Here is a description of zeineb the cat",
        "activelevel":3,
        "attentionSeeking": true,
        "neutered":false,
        "vaccinations":true,
        "abandonIssue":true
    },
    {
        "image":"Bob.png",
        "name":"Bob",
        "breed":"Dalmatian",
        "animal": "Dog",
        "gender":"Male",
        "age": "12",
        "animalId": "A112233",
        "shelterId":"S123456",
        "indoor":false,
        "outdoor":true,
        "description":"Write stuff here describing dog",
        "activelevel":10,
        "attentionSeeking": true,
        "neutered":true,
        "vaccinations":true,
        "abandonIssue":false
    },
    {
        "image":"Ari.png",
        "name":"Ari",
        "breed":"Pigeon",
        "animal": "Bird",
        "gender":"Male",
        "age": "45",
        "animalId": "A111111",
        "shelterId":"S123456",
        "indoor":true,
        "outdoor":false,
        "description":"Here is a description ",
        "activelevel":1,
        "attentionSeeking":false,
        "neutered":false,
        "vaccinations":true,
        "abandonIssue":true
    },
    {
        "image":"Sam.png",
        "name":"Sam",
        "breed":"Tarantula",
        "animal": "Spider",
        "gender":"Male",
        "age": "10",
        "animalId": "A222222",
        "shelterId":"S123456",
        "indoor":true,
        "outdoor":false,
        "description":"Here is a description ",
        "activelevel":2,
        "attentionSeeking": true,
        "neutered":false,
        "vaccinations":false,
        "abandonIssue":false
    },
    {
        "image":"Faith.png",
        "name":"Faith",
        "breed":"Pomeranian",
        "animal": "Dog",
        "gender":"Female",
        "age": "1",
        "animalId": "A333333",
        "shelterId":"S123456",
        "indoor":false,
        "outdoor":true,
        "description":"Here is a description ",
        "activelevel": 8,
        "attentionSeeking": true,
        "neutered":true,
        "vaccinations":true,
        "abandonIssue":false
    },
    {
        "image":"Carlota.png",
        "name":"Carlota",
        "breed":"Calico",
        "animal": "Cat",
        "gender":"Female",
        "age": "1",
        "animalId": "A123466",
        "shelterId":"S112233",
        "indoor":false,
        "outdoor":true,
        "description":"Here is a description ",
        "activelevel":5,
        "attentionSeeking": true,
        "neutered":true,
        "vaccinations":true,
        "abandonIssue":false
    },
    {
        "image":"William.png",
        "name":"William",
        "breed":"Iguana",
        "animal": "Lizard",
        "gender":"Male",
        "age": "4",
        "animalId": "A123475",
        "shelterId":"S112233",
        "indoor":true,
        "outdoor":false,
        "description":"Here is a description ",
        "activelevel":3,
        "attentionSeeking": true,
        "neutered":true,
        "vaccinations":true,
        "abandonIssue":true
    },
    {
        "image":"Sadiyah.png",
        "name":"Sadiyah",
        "breed":"Daschund",
        "animal": "Dog",
        "gender":"Female",
        "age": "7",
        "animalId": "A123444",
        "shelterId":"S112233",
        "indoor":false,
        "outdoor":true,
        "description":"Here is a description ",
        "activelevel":7,
        "attentionSeeking": false,
        "neutered":true,
        "vaccinations":true,
        "abandonIssue":false
    },
    {
        "image":"Cheddar.png",
        "name":"Cheddar",
        "breed":"Corgi",
        "animal": "Dog",
        "gender":"Male",
        "age": "6",
        "animalId": "A123123",
        "shelterId":"S112233",
        "indoor":false,
        "outdoor":true,
        "description":"Here is a description ",
        "activelevel":3,
        "attentionSeeking": false,
        "neutered":true,
        "vaccinations":true,
        "abandonIssue":false
    },    
    {
        "image":"Milu.png",
         "name":"Milu",
        "breed":"Wire Fox Terrier",
        "animal": "Dog",
        "gender":"Male",
        "age": "9",
        "animalId": "A123421",
        "shelterId":"S112233",
        "indoor":false,
        "outdoor":true,
        "description":"Here is a description",
        "activelevel":9,
        "attentionSeeking": true,
        "neutered":true,
        "vaccinations":true,
        "abandonIssue":true
    },
    {
        "image":"Yato.png",
        "name":"Yato",
        "breed":"Munchkin",
        "animal": "Cat",
        "gender":"Male",
        "age": "15",
        "animalId": "A123422",
        "shelterId":"S112233",
        "indoor":true,
        "outdoor":false,
        "description":"Here is a description ",
        "activelevel":6,
        "attentionSeeking": true,
        "neutered":true,
        "vaccinations":true,
        "abandonIssue":true
    },
    {
        "image":"DrWhoo.png",
        "name":"Dr.Whoo",
        "breed":"Owl",
        "animal": "Bird",
        "gender":"Male",
        "age": "3",
        "animalId": "A123342",
        "shelterId":"S112233",
        "indoor":false,
        "outdoor":true,
        "description":"Here is a description ",
        "activelevel":6,
        "attentionSeeking": false,
        "neutered":true,
        "vaccinations":true,
        "abandonIssue":false
    },
    {
        "image":"Remmy.png",
        "name":"Remmy",
        "breed":"Dumbo",
        "animal": "Rat",
        "gender":"Male",
        "age": "2",
        "animalId": "A123111",
        "shelterId":"S112233",
        "indoor":true,
        "outdoor":false,
        "description":"Here is a description ",
        "activelevel":7,
        "attentionSeeking": false,
        "neutered":false,
        "vaccinations":false,
        "abandonIssue":false
    },
    {
        "image":"1.png",
        "name":"Darwin",
        "breed":"Tree Frog",
        "animal": "Frog",
        "gender":"Female",
        "age": "5",
        "animalId": "A123143",
        "shelterId":"S112233",
        "indoor":true,
        "outdoor":false,
        "description":"Here is a description ",
        "activelevel":3,
        "attentionSeeking": false,
        "neutered":true,
        "vaccinations":true,
        "abandonIssue":false
    },
    {
        "image":"Larry.png",
        "name":"Larry",
        "breed":"Border Collie",
        "animal": "Dog",
        "gender":"Female",
        "age": "7",
        "animalId": "A123456",
        "shelterId":"S112233",
        "indoor":false,
        "outdoor":true,
        "description":"Here is a description ",
        "activelevel":9,
        "attentionSeeking": true,
        "neutered":true,
        "vaccinations":true,
        "abandonIssue":false
    }
]